{
  "type": "Feature",
  "properties": {
    "iso:country":"TW",
    "name:eng_x_preferred":[
        "N.Y. Bagels Cafe"
    ],
    "wof:name":"N.Y. Bagels Cafe",
    "wof:placetype":"venue"
},
  "geometry": {"coordinates":[121.56861111111,25.032225],"type":"Point"}
}