{
  "type": "Feature",
  "properties": {
    "iso:country":"TW",
    "name:eng_x_preferred":[
        "Black Bear Coffee"
    ],
    "wof:name":"Black Bear Coffee",
    "wof:placetype":"venue"
},
  "geometry": {"coordinates":[121.565085,25.039693],"type":"Point"}
}