{
  "type": "Feature",
  "properties": {
    "name:eng_x_preferred":[
        "Black Bear Coffee"
    ],
    "wof:name":"Black Bear Coffee",
    "wof:placetype":"venue"
},
  "geometry": {"coordinates":[121.56508527778,25.039692888889],"type":"Point"}
}