{
  "type": "Feature",
  "properties": {
    "iso:country":"TW",
    "name:eng_x_preferred":[
        "Guang Hua Digital Plaza"
    ],
    "wof:name":"Guang Hua Digital Plaza",
    "wof:placetype":"venue"
},
  "geometry": {"coordinates":[121.532028,25.045199],"type":"Point"}
}