{
  "type": "Feature",
  "properties": {
    "name:eng_x_preferred":[
        "Guang Hua Digital Plaza"
    ],
    "wof:name":"Guang Hua Digital Plaza",
    "wof:placetype":"venue"
},
  "geometry": {"coordinates":[121.53202772141,25.045199318826],"type":"Point"}
}